FunctionalMaybe/__init__.py
FunctionalMaybe/empty.py
FunctionalMaybe/formatting.py
FunctionalMaybe/functional_maybe.py
functional_maybe-1.1.8.dist-info/LICENSE
functional_maybe-1.1.8.dist-info/METADATA
functional_maybe-1.1.8.dist-info/WHEEL
functional_maybe-1.1.8.dist-info/top_level.txt
functional_maybe-1.1.8.dist-info/RECORD
